alph/__init__.py
alph/combo.py
alph/core.py
alph/layers.py
alph/layout.py
alph/preproc.py
alph/util.py
alph-0.4.14.dist-info/METADATA
alph-0.4.14.dist-info/WHEEL
alph-0.4.14.dist-info/licenses/LICENSE
alph-0.4.14.dist-info/RECORD
