Metadata-Version: 2.4
Name: alph
Version: 0.4.14
Summary: alph
License: MIT
License-File: LICENSE
Author: Uros Rapajic
Requires-Python: >=3.9,<4.0
Classifier: License :: OSI Approved :: MIT License
Classifier: Programming Language :: Python :: 3
Classifier: Programming Language :: Python :: 3.9
Classifier: Programming Language :: Python :: 3.10
Classifier: Programming Language :: Python :: 3.11
Classifier: Programming Language :: Python :: 3.12
Classifier: Programming Language :: Python :: 3.13
Classifier: Programming Language :: Python :: 3.14
Provides-Extra: graphviz
Requires-Dist: altair (>=5.0.1)
Requires-Dist: networkx (>=2.6.3)
Requires-Dist: pandas (>=1.3.5)
Requires-Dist: pygraphviz (>=1.10) ; extra == "graphviz"
Requires-Dist: scikit-network (>=0.27.1)
Project-URL: Homepage, https://github.com/connectedcompany/alph
Project-URL: Repository, https://github.com/connectedcompany/alph
